Jui/__init__.py
Jui/module.py
Jui-0.1.dist-info/LICENSE
Jui-0.1.dist-info/METADATA
Jui-0.1.dist-info/WHEEL
Jui-0.1.dist-info/top_level.txt
Jui-0.1.dist-info/RECORD
